flux_dev_tools/server/__init__.py
flux_dev_tools/server/flask.py
flux_dev_tools/server/invoke.py
flux_dev_tools/server/serialization.py
flux_dev_tools/server/tests/serialization.py
rippling_flux_dev_tools-0.1.18.dist-info/METADATA
rippling_flux_dev_tools-0.1.18.dist-info/WHEEL
rippling_flux_dev_tools-0.1.18.dist-info/licenses/LICENSE
rippling_flux_dev_tools-0.1.18.dist-info/RECORD
