Metadata-Version: 2.4
Name: rippling-flux-dev-tools
Version: 0.1.18
Summary: Rippling Flux App development tools.
License-File: LICENSE
Author: Rippling Apps
Author-email: apps@rippling.com
Requires-Python: >=3.10,<4.0
Classifier: Programming Language :: Python :: 3
Classifier: Programming Language :: Python :: 3.10
Classifier: Programming Language :: Python :: 3.11
Classifier: Programming Language :: Python :: 3.12
Classifier: Programming Language :: Python :: 3.13
Classifier: Programming Language :: Python :: 3.14
Requires-Dist: Flask (>=2.3.3,<=3.0.2)
Requires-Dist: rippling-flux-sdk (>=0,<1)
Requires-Dist: werkzeug (==3.0.3)
